{
  "users": [],
  "walletRequests": [],
  "supportRequests": [],
  "chats": [],
  "games": [
    {"id":"dice","name":"Dice","category":"Egame","icon":"🎲","type":"builtin","playUrl":"#dice","enabled":true,"rtp":96},
    {"id":"mines","name":"Mines","category":"Egame","icon":"💣","type":"builtin","playUrl":"#mines","enabled":true,"rtp":96},
    {"id":"slots","name":"Slots","category":"Slot","icon":"🎰","type":"builtin","playUrl":"#slots","enabled":true,"rtp":95},
    {"id":"coinflip","name":"Coin Flip","category":"Egame","icon":"🪙","type":"builtin","playUrl":"#coinflip","enabled":true,"rtp":98},
    {"id":"blackjack","name":"Blackjack","category":"Casino","icon":"🃏","type":"builtin","playUrl":"#blackjack","enabled":true,"rtp":97},
    {"id":"roulette","name":"Roulette","category":"Casino","icon":"🎡","type":"builtin","playUrl":"#roulette","enabled":true,"rtp":94},
    {"id":"crash","name":"Crash","category":"Egame","icon":"🚀","type":"builtin","playUrl":"#crash","enabled":true,"rtp":96},
    {"id":"plinko","name":"Plinko","category":"Egame","icon":"🔻","type":"builtin","playUrl":"#plinko","enabled":true,"rtp":96}
  ],
  "promos": [{"id":"WELCOME","code":"WELCOME","title":"Welcome Bonus","bonus":100,"active":true,"image":"🎁"}],
  "notifications": [],
  "audit": [],
  "siteConfig": {"name":"AUSGG","tagline":"Play-money casino demo","primary":"#22c55e","mode":"dark","hero":"Premium play-money casino lobby","terms":"AUSGG is a study/demo play-money platform. No real-money gambling is provided."},
  "depositSettings": {"methods":[{"id":"bank","name":"Bank Transfer","instructions":"Transfer to demo bank account AUSGG-000 and upload receipt."},{"id":"crypto","name":"Crypto Demo","instructions":"Use demo wallet address only: DEMO-WALLET-123."}]},
  "withdrawalFields": [{"id":"fullName","label":"Full Name","type":"text","required":true},{"id":"bankName","label":"Bank Name","type":"text","required":true},{"id":"accountNumber","label":"Account Number","type":"text","required":true},{"id":"note","label":"Note","type":"textarea","required":false}],
  "adminSettings": {"requestTemplates":[{"id":"deposit-info","title":"Deposit Check Form","fields":["Amount","Method","Transaction ID","Note"]},{"id":"account-help","title":"Account Help Form","fields":["Issue","Details","Screenshot link"]}]}
}
